mosaik_components/pv/__init__.py
mosaik_components/pv/pvgis.py
mosaik_components/pv/pvgis_simulator.py
mosaik_pvgis-1.2.3.dist-info/AUTHORS.txt
mosaik_pvgis-1.2.3.dist-info/LICENSE
mosaik_pvgis-1.2.3.dist-info/METADATA
mosaik_pvgis-1.2.3.dist-info/WHEEL
mosaik_pvgis-1.2.3.dist-info/RECORD
