Metadata-Version: 2.3
Name: mosaik-pvgis
Version: 1.2.3
Summary: PVGIS Simulator for mosaik
License: LICENSE
Author: Danila Valko
Author-email: mosaik@offis.de
Requires-Python: >=3.9,<4.0
Classifier: License :: Other/Proprietary License
Classifier: Programming Language :: Python :: 3
Classifier: Programming Language :: Python :: 3.9
Classifier: Programming Language :: Python :: 3.10
Classifier: Programming Language :: Python :: 3.11
Classifier: Programming Language :: Python :: 3.12
Classifier: Programming Language :: Python :: 3.13
Requires-Dist: diskcache (>=5.6.3,<6.0.0)
Requires-Dist: mosaik-api-v3 (>=3.0.7,<4.0.0)
Requires-Dist: pandas
Requires-Dist: requests (>=2.31.0,<3.0.0)
Requires-Dist: tqdm (>=4.66.1,<5.0.0)
